setup.py
beixianlib/__init__.py
beixianlib/cz_clear.py
beixianlib/cz_pinyin.py
beixianlib/cz_print.py
beixianlib/cz_qrcode.py
beixianlib.egg-info/PKG-INFO
beixianlib.egg-info/SOURCES.txt
beixianlib.egg-info/dependency_links.txt
beixianlib.egg-info/top_level.txt