Metadata-Version: 2.1
Name: beixianlib
Version: 0.0.3
Summary: 北弦工作室专属库
Home-page: https://github.com/
Author: 李承泽（橙子室长）
Author-email: 3161399620@qq.com
License: UNKNOWN
Platform: UNKNOWN
Classifier: Programming Language :: Python :: 3
Classifier: License :: OSI Approved :: MIT License
Classifier: Operating System :: OS Independent
